{
  "family": "yarpapigateway-task",
  "networkMode": "awsvpc",
  "containerDefinitions": [
    {
      "name": "yarpapigateway-container",
      "image": "654654461467.dkr.ecr.ap-southeast-1.amazonaws.com/yarpapigateway-container:latest",
      "portMappings": [
        {
          "containerPort": 80,
          "protocol": "tcp"
        }
      ],
      "essential": true,
      "environment": [
        {
          "name": "ASPNETCORE_ENVIRONMENT",
          "value": "Development"
        }
      ]
    }
  ],
  "requiresCompatibilities": [
    "FARGATE"
  ],
  "cpu": "256",
  "memory": "512",
  "executionRoleArn": "arn:aws:iam::123456789012:role/ecsTaskExecutionRole"
}